sensingpy/__init__.py
sensingpy/enums.py
sensingpy/image.py
sensingpy/masks.py
sensingpy/plot.py
sensingpy/reader.py
sensingpy/selector.py
sensingpy/bathymetry/__init__.py
sensingpy/bathymetry/metrics.py
sensingpy/bathymetry/models.py
sensingpy/bathymetry/plot.py
sensingpy/preprocessing/__init__.py
sensingpy/preprocessing/deglinting.py
sensingpy/preprocessing/outliers.py
tests/__init__.py
tests/mask_test.py
tests/selector_test.py
sensingpy-3.0.0.dist-info/METADATA
sensingpy-3.0.0.dist-info/WHEEL
sensingpy-3.0.0.dist-info/top_level.txt
sensingpy-3.0.0.dist-info/RECORD
