Metadata-Version: 2.4
Name: sensingpy
Version: 3.0.0
Summary: A Python package for geospatial image processing and analysis.
Home-page: https://github.com/aouei/geopy
Author: Sergio Heredia
Author-email: Aouei <sergiohercar1@gmail.com>
Project-URL: Homepage, https://github.com/Aouei/sensingpy
Project-URL: Bug Tracker, https://github.com/Aouei/sensingpy/issues
Requires-Python: >=3.11
Requires-Dist: matplotlib
Requires-Dist: numpy
Requires-Dist: xarray
Requires-Dist: rasterio
Requires-Dist: pyproj
Requires-Dist: shapely
Requires-Dist: cartopy
Requires-Dist: contextily
Requires-Dist: scipy
Requires-Dist: seaborn
Dynamic: author
Dynamic: home-page
Dynamic: requires-python
